{
  "base": [
    "PowerBeam",
    "PowerSuit"
  ],
  "upgrades": [
    "Morph",
    "Bombs",
    "Charge",
    "HiJump",
    "Spazer",
    "Varia",
    "SpeedBooster",
    "Ice",
    "Grapple",
    "Wave",
    "XRayScope",
    "Gravity",
    "SpaceJump",
    "SpringBall",
    "Plasma",
    "ScrewAttack"
  ],
  "expansions": [
    "ETank",
    "Super",
    "Missile",
    "ReserveTank",
    "PowerBomb"
  ],
  "bosses": [
    "CeresRidley",
    "Ridley",
    "Kraid",
    "Draygon",
    "Phantoon",
    "MotherBrain"
  ],
  "flags": [
    "ZebesAwake",
    "Hyper"
  ]
}
