[
  {
    "id": 132,
    "name": "Main Hall",
    "area": "Lower Norfair",
    "subarea": "East",
    "note": "Room Object",
    "nodes": [
      {
        "id": 1,
        "name": "Door",
        "nodeType": "door",
        "note": "Door Object"
      },
      {
        "id": 2,
        "name": "Door",
        "nodeType": "door",
        "note": "Door Object"
      }
    ],
    "links": [
      {
        "from": 1,
        "to": [
          {
            "id": 2,
            "requires": [
              "canOpenYellowDoors",
              "canPassBombPassages"
            ],
            "unlock": null
          }
        ]
      }
    ]
  },
  {
    "id": 133,
    "name": "Fast Pillars Setup Room",
    "area": "Lower Norfair",
    "subarea": "East",
    "note": "Room Object",
    "nodes": [
      {
        "id": 1,
        "name": "Door",
        "nodeType": "door",
        "note": "Door Object"
      },
      {
        "id": 2,
        "name": "Door",
        "nodeType": "door",
        "note": "Door Object"
      }
    ],
    "links": [
      {
        "from": 1,
        "to": [
          {
            "id": 2,
            "requires": [
              "canOpenYellowDoors",
              "canPassBombPassages"
            ],
            "unlock": null
          }
        ]
      }
    ]
  },
  {
    "id": 134,
    "name": "Pillar Room",
    "area": "Lower Norfair",
    "subarea": "East",
    "note": "Room Object",
    "nodes": [
      {
        "id": 1,
        "name": "Door",
        "nodeType": "door",
        "note": "Door Object"
      },
      {
        "id": 2,
        "name": "Door",
        "nodeType": "door",
        "note": "Door Object"
      }
    ],
    "links": [
      {
        "from": 1,
        "to": [
          {
            "id": 2,
            "requires": [
              "canOpenYellowDoors",
              "canPassBombPassages"
            ],
            "unlock": null
          }
        ]
      }
    ]
  },
  {
    "id": 135,
    "name": "The Worst Room In The Game",
    "area": "Lower Norfair",
    "subarea": "East",
    "note": "Room Object",
    "nodes": [
      {
        "id": 1,
        "name": "Door",
        "nodeType": "door",
        "note": "Door Object"
      },
      {
        "id": 2,
        "name": "Door",
        "nodeType": "door",
        "note": "Door Object"
      }
    ],
    "links": [
      {
        "from": 1,
        "to": [
          {
            "id": 2,
            "requires": [
              "canOpenYellowDoors",
              "canPassBombPassages"
            ],
            "unlock": null
          }
        ]
      }
    ]
  },
  {
    "id": 136,
    "name": "Amphitheatre",
    "area": "Lower Norfair",
    "subarea": "East",
    "note": "Room Object",
    "nodes": [
      {
        "id": 1,
        "name": "Door",
        "nodeType": "door",
        "note": "Door Object"
      },
      {
        "id": 2,
        "name": "Door",
        "nodeType": "door",
        "note": "Door Object"
      }
    ],
    "links": [
      {
        "from": 1,
        "to": [
          {
            "id": 2,
            "requires": [
              "canOpenYellowDoors",
              "canPassBombPassages"
            ],
            "unlock": null
          }
        ]
      }
    ]
  },
  {
    "id": 137,
    "name": "Red Kihunter Shaft",
    "area": "Lower Norfair",
    "subarea": "East",
    "note": "Room Object",
    "nodes": [
      {
        "id": 1,
        "name": "Door",
        "nodeType": "door",
        "note": "Door Object"
      },
      {
        "id": 2,
        "name": "Door",
        "nodeType": "door",
        "note": "Door Object"
      }
    ],
    "links": [
      {
        "from": 1,
        "to": [
          {
            "id": 2,
            "requires": [
              "canOpenYellowDoors",
              "canPassBombPassages"
            ],
            "unlock": null
          }
        ]
      }
    ]
  },
  {
    "id": 138,
    "name": "Wasteland",
    "area": "Lower Norfair",
    "subarea": "East",
    "note": "Room Object",
    "nodes": [
      {
        "id": 1,
        "name": "Door",
        "nodeType": "door",
        "note": "Door Object"
      },
      {
        "id": 2,
        "name": "Door",
        "nodeType": "door",
        "note": "Door Object"
      }
    ],
    "links": [
      {
        "from": 1,
        "to": [
          {
            "id": 2,
            "requires": [
              "canOpenYellowDoors",
              "canPassBombPassages"
            ],
            "unlock": null
          }
        ]
      }
    ]
  },
  {
    "id": 139,
    "name": "Metal Pirates Room",
    "area": "Lower Norfair",
    "subarea": "East",
    "note": "Room Object",
    "nodes": [
      {
        "id": 1,
        "name": "Door",
        "nodeType": "door",
        "note": "Door Object"
      },
      {
        "id": 2,
        "name": "Door",
        "nodeType": "door",
        "note": "Door Object"
      }
    ],
    "links": [
      {
        "from": 1,
        "to": [
          {
            "id": 2,
            "requires": [
              "canOpenYellowDoors",
              "canPassBombPassages"
            ],
            "unlock": null
          }
        ]
      }
    ]
  },
  {
    "id": 140,
    "name": "Plowerhouse Room",
    "area": "Lower Norfair",
    "subarea": "East",
    "note": "Room Object",
    "nodes": [
      {
        "id": 1,
        "name": "Door",
        "nodeType": "door",
        "note": "Door Object"
      },
      {
        "id": 2,
        "name": "Door",
        "nodeType": "door",
        "note": "Door Object"
      }
    ],
    "links": [
      {
        "from": 1,
        "to": [
          {
            "id": 2,
            "requires": [
              "canOpenYellowDoors",
              "canPassBombPassages"
            ],
            "unlock": null
          }
        ]
      }
    ]
  },
  {
    "id": 141,
    "name": "Lower Norfair Farming Room",
    "area": "Lower Norfair",
    "subarea": "East",
    "note": "Room Object",
    "nodes": [
      {
        "id": 1,
        "name": "Door",
        "nodeType": "door",
        "note": "Door Object"
      },
      {
        "id": 2,
        "name": "Door",
        "nodeType": "door",
        "note": "Door Object"
      }
    ],
    "links": [
      {
        "from": 1,
        "to": [
          {
            "id": 2,
            "requires": [
              "canOpenYellowDoors",
              "canPassBombPassages"
            ],
            "unlock": null
          }
        ]
      }
    ]
  },
  {
    "id": 142,
    "name": "Ridley's Room",
    "area": "Lower Norfair",
    "subarea": "East",
    "note": "Room Object",
    "nodes": [
      {
        "id": 1,
        "name": "Door",
        "nodeType": "door",
        "note": "Door Object"
      },
      {
        "id": 2,
        "name": "Door",
        "nodeType": "door",
        "note": "Door Object"
      }
    ],
    "links": [
      {
        "from": 1,
        "to": [
          {
            "id": 2,
            "requires": [
              "canOpenYellowDoors",
              "canPassBombPassages"
            ],
            "unlock": null
          }
        ]
      }
    ]
  },
  {
    "id": 143,
    "name": "Ridley Tank Room",
    "area": "Lower Norfair",
    "subarea": "East",
    "note": "Room Object",
    "nodes": [
      {
        "id": 1,
        "name": "Door",
        "nodeType": "door",
        "note": "Door Object"
      },
      {
        "id": 2,
        "name": "Door",
        "nodeType": "door",
        "note": "Door Object"
      }
    ],
    "links": [
      {
        "from": 1,
        "to": [
          {
            "id": 2,
            "requires": [
              "canOpenYellowDoors",
              "canPassBombPassages"
            ],
            "unlock": null
          }
        ]
      }
    ]
  },
  {
    "id": 144,
    "name": "Mickey Mouse Room",
    "area": "Lower Norfair",
    "subarea": "East",
    "note": "Room Object",
    "nodes": [
      {
        "id": 1,
        "name": "Door",
        "nodeType": "door",
        "note": "Door Object"
      },
      {
        "id": 2,
        "name": "Door",
        "nodeType": "door",
        "note": "Door Object"
      }
    ],
    "links": [
      {
        "from": 1,
        "to": [
          {
            "id": 2,
            "requires": [
              "canOpenYellowDoors",
              "canPassBombPassages"
            ],
            "unlock": null
          }
        ]
      }
    ]
  },
  {
    "id": 145,
    "name": "Lower Norfair Fireflea Room",
    "area": "Lower Norfair",
    "subarea": "East",
    "note": "Room Object",
    "nodes": [
      {
        "id": 1,
        "name": "Door",
        "nodeType": "door",
        "note": "Door Object"
      },
      {
        "id": 2,
        "name": "Door",
        "nodeType": "door",
        "note": "Door Object"
      }
    ],
    "links": [
      {
        "from": 1,
        "to": [
          {
            "id": 2,
            "requires": [
              "canOpenYellowDoors",
              "canPassBombPassages"
            ],
            "unlock": null
          }
        ]
      }
    ]
  },
  {
    "id": 146,
    "name": "Lower Norfair Spring Ball Maze Room",
    "area": "Lower Norfair",
    "subarea": "East",
    "note": "Room Object",
    "nodes": [
      {
        "id": 1,
        "name": "Door",
        "nodeType": "door",
        "note": "Door Object"
      },
      {
        "id": 2,
        "name": "Door",
        "nodeType": "door",
        "note": "Door Object"
      }
    ],
    "links": [
      {
        "from": 1,
        "to": [
          {
            "id": 2,
            "requires": [
              "canOpenYellowDoors",
              "canPassBombPassages"
            ],
            "unlock": null
          }
        ]
      }
    ]
  },
  {
    "id": 147,
    "name": "Lower Norfair Escape Power Bomb Room",
    "area": "Lower Norfair",
    "subarea": "East",
    "note": "Room Object",
    "nodes": [
      {
        "id": 1,
        "name": "Door",
        "nodeType": "door",
        "note": "Door Object"
      },
      {
        "id": 2,
        "name": "Door",
        "nodeType": "door",
        "note": "Door Object"
      }
    ],
    "links": [
      {
        "from": 1,
        "to": [
          {
            "id": 2,
            "requires": [
              "canOpenYellowDoors",
              "canPassBombPassages"
            ],
            "unlock": null
          }
        ]
      }
    ]
  },
  {
    "id": 148,
    "name": "Three Muskateers' Room",
    "area": "Lower Norfair",
    "subarea": "East",
    "note": "Room Object",
    "nodes": [
      {
        "id": 1,
        "name": "Door",
        "nodeType": "door",
        "note": "Door Object"
      },
      {
        "id": 2,
        "name": "Door",
        "nodeType": "door",
        "note": "Door Object"
      }
    ],
    "links": [
      {
        "from": 1,
        "to": [
          {
            "id": 2,
            "requires": [
              "canOpenYellowDoors",
              "canPassBombPassages"
            ],
            "unlock": null
          }
        ]
      }
    ]
  },
  {
    "id": 149,
    "name": "Acid Statue Room",
    "area": "Lower Norfair",
    "subarea": "West",
    "note": "Room Object",
    "nodes": [
      {
        "id": 1,
        "name": "Door",
        "nodeType": "door",
        "note": "Door Object"
      },
      {
        "id": 2,
        "name": "Door",
        "nodeType": "door",
        "note": "Door Object"
      }
    ],
    "links": [
      {
        "from": 1,
        "to": [
          {
            "id": 2,
            "requires": [
              "canOpenYellowDoors",
              "canPassBombPassages"
            ],
            "unlock": null
          }
        ]
      }
    ]
  },
  {
    "id": 150,
    "name": "Golden Torizo's Room",
    "area": "Lower Norfair",
    "subarea": "West",
    "note": "Room Object",
    "nodes": [
      {
        "id": 1,
        "name": "Door",
        "nodeType": "door",
        "note": "Door Object"
      },
      {
        "id": 2,
        "name": "Door",
        "nodeType": "door",
        "note": "Door Object"
      }
    ],
    "links": [
      {
        "from": 1,
        "to": [
          {
            "id": 2,
            "requires": [
              "canOpenYellowDoors",
              "canPassBombPassages"
            ],
            "unlock": null
          }
        ]
      }
    ]
  },
  {
    "id": 151,
    "name": "Screw Attack Room",
    "area": "Lower Norfair",
    "subarea": "West",
    "note": "Room Object",
    "nodes": [
      {
        "id": 1,
        "name": "Door",
        "nodeType": "door",
        "note": "Door Object"
      },
      {
        "id": 2,
        "name": "Door",
        "nodeType": "door",
        "note": "Door Object"
      }
    ],
    "links": [
      {
        "from": 1,
        "to": [
          {
            "id": 2,
            "requires": [
              "canOpenYellowDoors",
              "canPassBombPassages"
            ],
            "unlock": null
          }
        ]
      }
    ]
  },
  {
    "id": 152,
    "name": "Golden Torizo Energy Recharge",
    "area": "Lower Norfair",
    "subarea": "West",
    "note": "Room Object",
    "nodes": [
      {
        "id": 1,
        "name": "Door",
        "nodeType": "door",
        "note": "Door Object"
      },
      {
        "id": 2,
        "name": "Door",
        "nodeType": "door",
        "note": "Door Object"
      }
    ],
    "links": [
      {
        "from": 1,
        "to": [
          {
            "id": 2,
            "requires": [
              "canOpenYellowDoors",
              "canPassBombPassages"
            ],
            "unlock": null
          }
        ]
      }
    ]
  },
  {
    "id": 153,
    "name": "Fast Ripper Room",
    "area": "Lower Norfair",
    "subarea": "West",
    "note": "Room Object",
    "nodes": [
      {
        "id": 1,
        "name": "Door",
        "nodeType": "door",
        "note": "Door Object"
      },
      {
        "id": 2,
        "name": "Door",
        "nodeType": "door",
        "note": "Door Object"
      }
    ],
    "links": [
      {
        "from": 1,
        "to": [
          {
            "id": 2,
            "requires": [
              "canOpenYellowDoors",
              "canPassBombPassages"
            ],
            "unlock": null
          }
        ]
      }
    ]
  }
]
