{
  "id": 16,
  "name": "Crateria Save Room",
  "area": "Crateria",
  "subarea": "Central",
  "playable": true,
  "roomAddress": "0x793D5",
  "roomEnvironments": [
    {"heated": false}
  ],
  "nodes": [
    {
      "id": 1,
      "name": "Crateria Save Room Door (to Parlor)",
      "nodeType": "door",
      "nodeSubType": "blue",
      "nodeAddress": "0x00189be",
      "doorEnvironments": [
        {"physics": "air"}
      ]
    },
    {
      "id": 2,
      "name": "Crateria Save Station",
      "utility": ["save"],
      "nodeType": "utility",
      "nodeSubType": "save"
    }
  ],
  "enemies": [],
  "strats": [
    {
      "from": 1,
      "to": 1,
      "name": "Leave with Runway",
      "notable": false,
      "requires": [],
      "exitCondition": {
        "leaveWithRunway": {
          "length": 4,
          "openEnd": 1
        }
      }
    },
    {
      "from": 1,
      "to": 2,
      "name": "Base",
      "notable": false,
      "requires": []
    },
    {
      "from": 2,
      "to": 1,
      "name": "Base",
      "notable": false,
      "requires": []
    }
  ]
}