{
  "$schema": "../../../schema/m3-room.schema.json",
  "id": 16,
  "name": "Crateria Save Room",
  "area": "Crateria",
  "subarea": "Central",
  "roomAddress": "0x793D5",
  "roomEnvironments": [{"heated": false}],
  "mapTileMask": [
    [1]
  ],
  "nodes": [
    {
      "id": 1,
      "name": "Right Door",
      "nodeType": "door",
      "nodeSubType": "blue",
      "nodeAddress": "0x00189be",
      "doorOrientation": "right",
      "doorEnvironments": [{"physics": "air"}],
      "mapTileMask": [
        [2]
      ]
    },
    {
      "id": 2,
      "name": "Save Station",
      "nodeType": "utility",
      "nodeSubType": "save",
      "utility": ["save"],
      "mapTileMask": [
        [2]
      ]
    }
  ],
  "enemies": [],
  "strats": [
    {
      "id": 1,
      "link": [1, 1],
      "name": "Leave with Runway",
      "requires": [],
      "exitCondition": {
        "leaveWithRunway": {
          "length": 4,
          "openEnd": 1
        }
      },
      "flashSuitChecked": true,
      "blueSuitChecked": true
    },
    {
      "id": 2,
      "link": [1, 1],
      "name": "Crystal Flash",
      "requires": [
        "h_CrystalFlash"
      ],
      "flashSuitChecked": true,
      "blueSuitChecked": true
    },
    {
      "id": 5,
      "link": [1, 1],
      "name": "Come in Shinecharging, Crystal Spark",
      "entranceCondition": {
        "comeInShinecharging": {
          "length": 3,
          "openEnd": 0
        },
        "comesInHeated": "no"
      },
      "requires": [
        "h_CrystalSparkWithoutLenience"
      ],
      "flashSuitChecked": true,
      "blueSuitChecked": true,
      "devNote": ["No lenience, because reloading from the save is possible."]
    },
    {
      "id": 3,
      "link": [1, 2],
      "name": "Base",
      "requires": [],
      "flashSuitChecked": true,
      "blueSuitChecked": true
    },
    {
      "id": 4,
      "link": [2, 1],
      "name": "Base",
      "requires": [],
      "flashSuitChecked": true,
      "blueSuitChecked": true
    }
  ],
  "notables": [],
  "nextStratId": 6,
  "nextNotableId": 1
}